pinn_pytorch/__init__.py
pinn_pytorch/boundary_conditions.py
pinn_pytorch/derivatives.py
pinn_pytorch/model.py
pinn_pytorch/training_settings.py
pinn_pytorch-0.0.5.dist-info/METADATA
pinn_pytorch-0.0.5.dist-info/WHEEL
pinn_pytorch-0.0.5.dist-info/top_level.txt
pinn_pytorch-0.0.5.dist-info/RECORD
